folder_indexer/__init__.py
folder_indexer/__main__.py
folder_indexer/indexer.py
folder_indexer-0.2.3.dist-info/METADATA
folder_indexer-0.2.3.dist-info/WHEEL
folder_indexer-0.2.3.dist-info/entry_points.txt
folder_indexer-0.2.3.dist-info/licenses/LICENSE
folder_indexer-0.2.3.dist-info/RECORD
