Metadata-Version: 2.4
Name: folder_indexer
Version: 0.2.3
Summary: A Python script to index a large folder structure into a parquet file, along with metadata
Project-URL: Homepage, https://github.com/RecRanger/folder-indexer-py
Project-URL: Issues, https://github.com/RecRanger/folder-indexer-py/issues
Author-email: RecRanger <RecRanger+package@proton.me>
License-Expression: BSD-3-Clause
License-File: LICENSE
Classifier: License :: OSI Approved :: BSD License
Classifier: Operating System :: OS Independent
Classifier: Programming Language :: Python :: 3
Requires-Python: >=3.10
Requires-Dist: loguru>0.7.0
Requires-Dist: polars>1.30
Requires-Dist: python-magic>=0.4.27
Requires-Dist: tqdm>=4.65.0
